{
  "title": "Light Housekeeping & Home Support",
  "shortTitle": "Housekeeping",
  "order": 3,
  "icon": "broom",
  "summary": "A clean, safe, comfortable home — laundry, tidying, meal prep, and the everyday tasks that get harder with age.",
  "intro": "A tidy, organized home is more than appearance — it is safety, comfort, and pride. Our caregivers handle the everyday tasks that have become difficult, so your loved one can relax in a space that feels cared for. From a home-cooked meal to fresh laundry, we help maintain the warmth and order that make a house feel like home.",
  "includes": [
    "Light cleaning, dusting, and tidying",
    "Laundry, linens, and ironing",
    "Meal planning and home-cooked meal preparation",
    "Dishes and kitchen cleanup",
    "Grocery shopping and errands",
    "Reducing fall hazards and keeping walkways clear"
  ],
  "helps": [
    "Seniors who find housework physically tiring or unsafe",
    "Loved ones who skip meals or struggle to cook",
    "Families wanting a safer, clutter-free living space",
    "Anyone who simply deserves a little more ease at home"
  ],
  "expect": [
    "Tasks chosen around your loved one's needs and home",
    "Respect for their belongings, space, and preferences",
    "Nutritious meals that suit dietary needs and tastes",
    "A consistent caregiver who learns your household routine"
  ],
  "metaDescription": "Light housekeeping and home support for seniors — cleaning, laundry, meal preparation, errands, and a safer home, all handled with care and respect."
}
